bloom_cascade/__init__.py
bloom_cascade/cascade.py
bloom_cascade-1.0.5.dist-info/METADATA
bloom_cascade-1.0.5.dist-info/WHEEL
bloom_cascade-1.0.5.dist-info/top_level.txt
bloom_cascade-1.0.5.dist-info/RECORD
