Metadata-Version: 2.4
Name: bloom_cascade
Version: 1.0.5
Requires-Dist: rbloom==1.5.2
Dynamic: description
Dynamic: description-content-type
Dynamic: requires-dist
